metar_decoder/__init__.py
metar_decoder/cli.py
metar_decoder/datatypes.py
metar_decoder/decoder.py
metar_decoder/regex_patterns.py
metar_decoder/utils.py
metar_decoder/weather_utils.py
metar_decoder-1.0.2.dist-info/licenses/LICENSE
metar_decoder-1.0.2.dist-info/METADATA
metar_decoder-1.0.2.dist-info/WHEEL
metar_decoder-1.0.2.dist-info/entry_points.txt
metar_decoder-1.0.2.dist-info/top_level.txt
metar_decoder-1.0.2.dist-info/RECORD
