Metadata-Version: 2.4
Name: metar_decoder
Version: 1.0.2
Summary: Decodificador METAR en Python
Author-email: Christian Dávila <cadv.met.92@gmail.com>
License: MIT License
Project-URL: Homepage, https://github.com/CADV92/metar_decoder
Project-URL: Issues, https://github.com/CADV92/metar_decoder/issues
Classifier: Programming Language :: Python :: 3
Classifier: License :: OSI Approved :: MIT License
Classifier: Operating System :: OS Independent
Classifier: Topic :: Scientific/Engineering :: Atmospheric Science
Requires-Python: >=3.9
License-File: LICENSE
Dynamic: license-file
